setup.py
pylutron_qse/__init__.py
pylutron_qse/devices.py
pylutron_qse/qse.py
pylutron_qse.egg-info/PKG-INFO
pylutron_qse.egg-info/SOURCES.txt
pylutron_qse.egg-info/dependency_links.txt
pylutron_qse.egg-info/top_level.txt